spackle/__init__.py
spackle/constants.py
spackle/customer.py
spackle/exceptions.py
spackle/log.py
spackle/pricing_table.py
spackle/stores/__init__.py
spackle/stores/api.py
spackle/stores/base.py
spackle/stores/file.py
spackle/stores/memory.py
spackle/waiters.py
spackle_python-0.0.45.dist-info/LICENSE
spackle_python-0.0.45.dist-info/METADATA
spackle_python-0.0.45.dist-info/WHEEL
spackle_python-0.0.45.dist-info/RECORD
