Metadata-Version: 2.1
Name: spackle-python
Version: 0.0.45
Summary: 
Author: Hunter Clarke
Author-email: hunter@spackle.so
Requires-Python: >=3.9,<4.0
Classifier: Programming Language :: Python :: 3
Classifier: Programming Language :: Python :: 3.9
Classifier: Programming Language :: Python :: 3.10
Classifier: Programming Language :: Python :: 3.11
Requires-Dist: requests (>=2.31.0,<3.0.0)
Requires-Dist: six (>=1.16.0,<2.0.0)
Requires-Dist: stripe (>=5.2.0,<6.0.0)
